sense_voice_streaming_asr/__init__.py
sense_voice_streaming_asr/cmvn_utils.py
sense_voice_streaming_asr/model_data.py
sense_voice_streaming_asr/rolling_buffer.py
sense_voice_streaming_asr/sense_voice_streaming_asr.py
sense_voice_streaming_asr/models/SenseVoiceSmall/README.md
sense_voice_streaming_asr/models/SenseVoiceSmall/am.mvn
sense_voice_streaming_asr/models/SenseVoiceSmall/config.yaml
sense_voice_streaming_asr/models/SenseVoiceSmall/configuration.json
sense_voice_streaming_asr/models/SenseVoiceSmall/model_quant.onnx
sense_voice_streaming_asr/models/SenseVoiceSmall/tokens.json
sense_voice_streaming_asr/models/speech_fsmn_vad_zh-cn-16k-common-onnx/README.md
sense_voice_streaming_asr/models/speech_fsmn_vad_zh-cn-16k-common-onnx/am.mvn
sense_voice_streaming_asr/models/speech_fsmn_vad_zh-cn-16k-common-onnx/config.yaml
sense_voice_streaming_asr/models/speech_fsmn_vad_zh-cn-16k-common-onnx/configuration.json
sense_voice_streaming_asr/models/speech_fsmn_vad_zh-cn-16k-common-onnx/model_quant.onnx
sense_voice_streaming_asr/models/speech_fsmn_vad_zh-cn-16k-common-onnx/quickstart.md
sense_voice_streaming_asr-0.1.1.dist-info/LICENSE
sense_voice_streaming_asr-0.1.1.dist-info/METADATA
sense_voice_streaming_asr-0.1.1.dist-info/WHEEL
sense_voice_streaming_asr-0.1.1.dist-info/top_level.txt
sense_voice_streaming_asr-0.1.1.dist-info/RECORD
