Metadata-Version: 2.1
Name: sense-voice-streaming-asr
Version: 0.1.1
Summary: Real-time streaming automatic speech recognition (ASR) with support for Chinese, English, Cantonese, Japanese, and Korean languages using SenseVoiceSmall model.
Author-email: nikoseven <nikoseven@outlook.com>
Maintainer-email: nikoseven <nikoseven@outlook.com>
License: Apache-2.0
Project-URL: Homepage, https://github.com/nikoseven/sense-voice-streaming-asr
Project-URL: Repository, https://github.com/nikoseven/sense-voice-streaming-asr
Project-URL: Documentation, https://github.com/nikoseven/sense-voice-streaming-asr#readme
Project-URL: Bug Tracker, https://github.com/nikoseven/sense-voice-streaming-asr/issues
Keywords: speech-recognition,asr,streaming,real-time,sensevoice,multilingual,chinese,english,japanese,korean,cantonese,voice-processing,audio-processing,artificial-intelligence,machine-learning
Classifier: Development Status :: 4 - Beta
Classifier: Intended Audience :: Developers
Classifier: Intended Audience :: Science/Research
Classifier: Topic :: Scientific/Engineering :: Artificial Intelligence
Classifier: Topic :: Multimedia :: Sound/Audio :: Speech
Classifier: Topic :: Software Development :: Libraries :: Python Modules
Classifier: Topic :: Software Development :: Libraries
Classifier: License :: OSI Approved :: Apache Software License
Classifier: Programming Language :: Python :: 3
Classifier: Programming Language :: Python :: 3.8
Classifier: Programming Language :: Python :: 3.9
Classifier: Programming Language :: Python :: 3.10
Classifier: Programming Language :: Python :: 3.11
Classifier: Programming Language :: Python :: 3.12
Classifier: Programming Language :: Python :: 3.13
Classifier: Programming Language :: Python :: 3 :: Only
Classifier: Operating System :: OS Independent
Classifier: Natural Language :: Chinese (Simplified)
Classifier: Natural Language :: English
Classifier: Natural Language :: Japanese
Classifier: Natural Language :: Korean
Requires-Python: >=3.8
License-File: LICENSE
Requires-Dist: numpy
Requires-Dist: kaldi-native-fbank
Requires-Dist: sounddevice
Requires-Dist: sentencepiece
